Workbook

Sheet Resumen
A1: Acuarius — costos y proyección
A2: Plataforma de CRM y marketing con IA para pymes y agencias en LatAm
A3: Actualizado con facturas reales · Septiembre de 2026 · Cifras en dólares
A5: El negocio en cinco números | E5: Qué hay en cada hoja
A6: Precio medio por cliente al mes | B6: =Supuestos!B8 | C6: Mezclando planes de $39 y $99 | E6: Supuestos
A7: Lo que cuesta atenderlo | B7: =Supuestos!B17 | C7: Servidores, IA, correos e imágenes | E7: Todos los números que se pueden cambiar. Empieza aquí.
A8: Lo que cuesta cobrarle | B8: =Supuestos!B13 | C8: Comisión de la pasarela de pago
A9: Utilidad por cliente al mes | B9: =Supuestos!B8-Supuestos!B17-Supuestos!B13 | C9: Antes de costos fijos y marketing | E9: Costos
A10: Margen por cliente | B10: =IF(Supuestos!B8=0,0,(Supuestos!B8-Supuestos!B17-Supuestos!B13)/Supuestos!B8) | C10: De cada dólar que entra, cuánto queda | E10: Lo que se paga cada mes y el precio de cada cosa que consume un cliente. Marca qué está medido y qué estimado.
A12: El cliente que ya paga (datos reales) | E12: Margen
A13: Certain Pezzano paga al mes | B13: =Supuestos!B6 | E13: Cuánto deja un cliente. La primera columna es el cliente REAL, medido.
A14: Cuesta atenderlo | B14: =Margen!B12
A15: Comisión de cobro (Hotmart) | B15: =Margen!B14 | E15: Proyeccion
A16: Deja al mes | B16: =Margen!B15 | E16: 24 meses de clientes, ingresos, utilidad y la parte del socio.
A17: Margen real | B17: =Margen!B16
A18: Usa el CRM a diario (443 actividades en 30 días) pero aún no los agentes de IA.
E19: Lo que hay que saber antes de creerse esto
A20: A dónde puede llegar | E20: · Los costos fijos ya NO son estimados: salen de la factura de Vercel y del plan de Supabase contratado.
A21: Clientes al cerrar el año 1 | B21: =Proyeccion!D18 | E21: · El costo de los agentes de IA sigue siendo el único rubro grande sin medir, porque nadie los ha usado.
A22: Ingresos del mes 12 | B22: =Proyeccion!E18 | E22: · El crecimiento NO es un dato: son referencias del sector. Hoy hay un cliente pagando.
A23: Utilidad del mes 12 | B23: =Proyeccion!K18 | E23: · La utilidad no descuenta sueldos ni impuestos, que dependen de cómo se organice la sociedad.
A24: Clientes al cerrar el año 2 | B24: =Proyeccion!D30
A25: Utilidad del mes 24 | B25: =Proyeccion!K30 | E25: Amarillo = se puede cambiar. Verde = dato real medido.
A26: Utilidad acumulada en 24 meses | B26: =Proyeccion!M30
A28: Para el socio
A29: Participación (cambia este número) | B29: =Supuestos!B27 | C29: Se edita en la hoja Supuestos, celda B27
A30: Le corresponde en el mes 12 | B30: =Proyeccion!M18
A31: Le corresponde en el mes 24 | B31: =Proyeccion!M30
A32: Acumulado a 24 meses | B32: =Proyeccion!N30
A33: Al ritmo del mes 24, al año equivale a | B33: =Proyeccion!L30*12

Sheet Supuestos
A1: Supuestos del modelo
A2: Cambia solo las celdas AMARILLAS. Todo lo demás se recalcula solo.
A4: PRECIOS
A5: Precio del plan Pro (al mes) | B5: 39 | C5: Lo que se cobra hoy
A6: Precio del plan Agency (al mes) | B6: 99 | C6: Lo que se cobra hoy
A7: De cada 10 clientes, cuántos son Agency | B7: 0.2 | C7: Mezcla esperada de la cartera
A8: Precio medio por cliente | B8: =B5*(1-B7)+B6*B7 | C8: Se calcula solo: promedio ponderado
A10: CÓMO SE COBRA (la palanca más grande del modelo)
A11: Comisión de la pasarela (%) | B11: 0.099 | C11: Hotmart 9,9% · Stripe 2,9% · MercadoPago 3,49%
A12: Comisión fija por cada cobro | B12: 1 | C12: Hotmart $1,00 · Stripe $0,30 · MercadoPago $0,30
A13: Se lleva de cada cliente | B13: =B8*B11+B12 | C13: Cambia las dos de arriba y mira este número
A15: COSTOS
A16: Costo fijo de la plataforma (al mes) | B16: =Costos!B18 | C16: Ver la hoja Costos. Cifras REALES de septiembre
A17: Costo variable por cliente (al mes) | B17: =Margen!F12 | C17: Promedio ponderado Pro/Agency. Ver la hoja Margen
A19: CRECIMIENTO
A20: Clientes nuevos el primer mes | B20: 6 | C20: Con contenidos, eventos y publicidad arrancando
A21: Cuánto crece la captación cada mes | B21: 0.16 | C21: Un 16% más de altas cada mes que el anterior
A22: Cuántos se van cada mes (bajas) | B22: 0.055 | C22: De cada 100 clientes, 5 o 6 se dan de baja al mes
A23: Inversión en marketing (al mes) | B23: 0 | C23: Ponlo en 0 para ver solo la plataforma. Con $900 el mes 1 da −$715
A24: Tope de altas al mes | B24: 60 | C24: Techo realista: nadie capta infinito
A26: SOCIEDAD
A27: Participación del socio | B27: 0.3 | C27: ← ESTA es la celda para jugar. Mira la hoja Proyección
A30: De dónde salen los números
A31: · Costos fijos: la factura REAL de Vercel (7 sep 2026) y el plan de Supabase contratado el 1 de septiembre.
A32: · Costo de una imagen y del bot del inbox: MEDIDOS en la propia plataforma, no estimados.
A33: · Costo del chat con agentes: sigue siendo una ESTIMACIÓN — ningún cliente lo ha usado todavía.
A34: · Crecimiento y bajas: referencias de SaaS pequeño en LatAm. Son los números MENOS firmes del modelo.
A35: · Todo en dólares, sin impuestos ni IVA, que dependen del país.

Sheet Costos
A1: Costos fijos de la plataforma
A2: Lo que cuesta tener Acuarius encendido, haya 1 cliente o 300. Cifras de la factura de septiembre de 2026.
A4: Servicio | B4: Para qué | C4: Al mes | D4: ¿Real o previsto? | E4: Nota
A5: Vercel Pro | B5: Donde vive la aplicación | C5: 20 | D5: REAL | E5: Factura del 7 de septiembre
A6: Vercel — builds | B6: CPU de cada despliegue | C6: 1.3 | D6: PREVISTO | E6: Era $9,54 con la máquina «turbo»; bajada a «standard» el 8/09
A7: Supabase Pro | B7: La base de datos y sus respaldos | C7: 25 | D7: REAL | E7: Contratado el 1 de septiembre. Sin esto no hay copias de seguridad
A8: Resend | B8: El envío de correos | C8: 0 | D8: REAL | E8: Gratuito: se usa el 4% del cupo (110 de 3.000 correos al mes)
A9: Clerk | B9: Las cuentas y contraseñas | C9: 0 | D9: REAL | E9: Gratis hasta 10.000 usuarios activos
A10: Dominio | B10: acuarius.app | C10: 1.5 | D10: REAL | E10: Prorrateado del pago anual
A11: TOTAL AL MES | C11: =SUM(C5:C10)
A13: Lo que demuestra la factura real
A14: De los $29,99 que cobró Vercel en agosto, $9,54 fueron CPU de nuestros propios despliegues (260 en el mes) y solo $0,20 fue atender a los clientes: 66.107 llamadas a la API costaron 2 centavos y 0,28 GB de tráfico, 1 centavo. Es decir: el costo de Vercel es de DESARROLLO, no de operación, y no crece cuando entran clientes. Con la máquina de build corregida, esa partida baja de $9,54 a cerca de $1,30.
A18: Costo fijo usado en la proyección | B18: =C11
A21: Lo que cuesta cada cosa que hace un cliente
A22: Los ladrillos con los que se arma el costo de cada cliente. Fíjate en la columna de la derecha.
A24: Concepto | B24: Cuesta | C24: Unidad | D24: Proveedor | E24: ¿Medido o estimado?
A25: Mensaje a un agente IA | B25: 0.0389 | C25: por mensaje | D25: Anthropic | E25: ESTIMADO — ningún cliente ha usado los agentes todavía
A26: Respuesta del bot del inbox | B26: 0.0019 | C26: por mensaje | D26: Anthropic | E26: MEDIDO en la plataforma (corre en Haiku, prompt corto)
A27: Imagen con IA | B27: 0.06 | C27: por imagen | D27: fal.ai | E27: MEDIDO: 4 imágenes registradas, $0,06 exactos cada una
A28: Video con IA | B28: 0.45 | C28: por video | D28: BytePlus | E28: ESTIMADO — tarifa de lista de Seedance 2.0
A29: Correo de campaña | B29: 0.0004 | C29: por correo | D29: Resend | E29: ESTIMADO — $20 por 50.000 correos del plan de pago
A30: Un usuario en la cuenta | B30: 0.1 | C30: por usuario al mes | D30: Vercel+Supabase | E30: MEDIDO a la baja: toda la plataforma costó $0,20 en agosto
A31: Mil contactos guardados | B31: 0.2 | C31: por 1.000 al mes | D31: Supabase | E31: ESTIMADO — la base entera ocupa 26 MB de 8 GB incluidos
A34: El mensaje a un agente es 20 veces más caro que la respuesta del bot del inbox, y es el mismo modelo: la diferencia está en el tamaño del texto de instrucciones que se le manda. Es también el ÚNICO rubro grande que sigue sin medirse, porque ningún cliente ha usado los agentes.

Sheet Margen
A1: Cuánto deja cada cliente
A2: La primera columna NO es un supuesto: es el consumo medido de Certain Pezzano en 30 días. Las demás son perfiles para proyectar. Cambia las cantidades amarillas y mira el margen.
A4: Qué consume al mes | B4: CERTAIN PEZZANO (real, medido) | C4: Pro típico | D4: Agency típico | E4: Agency intenso | F4: Media de la cartera
A5: Usuarios en la cuenta | B5: 2 | C5: 3 | D5: 9 | E5: 10
A6: Contactos guardados (miles) | B6: 0.079 | C6: 1 | D6: 5 | E6: 5
A7: Mensajes a los agentes | B7: 0 | C7: 40 | D7: 60 | E7: 400
A8: Chats atendidos por el bot | B8: 0 | C8: 400 | D8: 800 | E8: 2500
A9: Imágenes generadas | B9: 0 | C9: 15 | D9: 10 | E9: 60
A10: Videos generados | B10: 0 | C10: 2 | D10: 1 | E10: 5
A11: Correos enviados | B11: 49 | C11: 2000 | D11: 6000 | E11: 12000
A12: Costo variable del cliente | B12: =B5*Costos!$B$30+B6*Costos!$B$31+B7*Costos!$B$25+B8*Costos!$B$26+B9*Costos!$B$27+B10*Costos!$B$28+B11*Costos!$B$29 | C12: =C5*Costos!$B$30+C6*Costos!$B$31+C7*Costos!$B$25+C8*Costos!$B$26+C9*Costos!$B$27+C10*Costos!$B$28+C11*Costos!$B$29 | D12: =D5*Costos!$B$30+D6*Costos!$B$31+D7*Costos!$B$25+D8*Costos!$B$26+D9*Costos!$B$27+D10*Costos!$B$28+D11*Costos!$B$29 | E12: =E5*Costos!$B$30+E6*Costos!$B$31+E7*Costos!$B$25+E8*Costos!$B$26+E9*Costos!$B$27+E10*Costos!$B$28+E11*Costos!$B$29 | F12: =(C12*(1-Supuestos!$B$7))+(D12*Supuestos!$B$7)
A13: Precio que paga | B13: =Supuestos!$B$6 | C13: =Supuestos!$B$5 | D13: =Supuestos!$B$6 | E13: =Supuestos!$B$6 | F13: =Supuestos!$B$8
A14: Comisión de cobro | B14: =B13*Supuestos!$B$11+Supuestos!$B$12 | C14: =C13*Supuestos!$B$11+Supuestos!$B$12 | D14: =D13*Supuestos!$B$11+Supuestos!$B$12 | E14: =E13*Supuestos!$B$11+Supuestos!$B$12 | F14: =F13*Supuestos!$B$11+Supuestos!$B$12
A15: UTILIDAD | B15: =B13-B12-B14 | C15: =C13-C12-C14 | D15: =D13-D12-D14 | E15: =E13-E12-E14 | F15: =F13-F12-F14
A16: MARGEN | B16: =IF(B13=0,0,B15/B13) | C16: =IF(C13=0,0,C15/C13) | D16: =IF(D13=0,0,D15/D13) | E16: =IF(E13=0,0,E15/E13) | F16: =IF(F13=0,0,F15/F13)
A18: Por qué el cliente real deja tanto más de lo que dice el modelo
A19: Porque no usa las funciones caras. En 30 días hizo 443 actividades de CRM y 55 tareas —usa la plataforma a diario— pero cero mensajes a los agentes, cero imágenes, cero videos y cero conversaciones de inbox (WhatsApp sigue bloqueado por Meta). Su costo real de servicio no llega a $1 al mes. Si mañana empieza a usar los agentes, el costo sube: por eso están las otras tres columnas.
A22: La media de la cartera (última columna) mezcla Pro típico y Agency típico según el % de la hoja Supuestos, y es la que usa la proyección.

Sheet Proyeccion
A1: Proyección a 24 meses
A2: Todo sale de la hoja Supuestos. Cambia la participación del socio allí (celda B27) y las dos últimas columnas se recalculan solas.
A4: Participación del socio: | C4: =Supuestos!B27 | D4: ← se cambia en la hoja Supuestos
A6: Mes | B6: Altas | C6: Bajas | D6: Clientes activos | E6: Ingresos | F6: Comisión de cobro | G6: Costo variable | H6: Costo fijo plataforma | I6: UTILIDAD DE OPERACIÓN | J6: Marketing | K6: Utilidad final | L6: Utilidad acumulada | M6: Socio del mes | N6: Socio acumulado
A7: 1 | B7: =MIN(Supuestos!$B$24,ROUND(Supuestos!$B$20*(1+Supuestos!$B$21)^0,0)) | C7: =0 | D7: =B7-C7 | E7: =D7*Supuestos!$B$8 | F7: =E7*Supuestos!$B$11+D7*Supuestos!$B$12 | G7: =D7*Supuestos!$B$17 | H7: =Supuestos!$B$16 | I7: =E7-F7-G7-H7 | J7: =Supuestos!$B$23 | K7: =I7-J7 | L7: =K7 | M7: =K7*Supuestos!$B$27 | N7: =M7
A8: 2 | B8: =MIN(Supuestos!$B$24,ROUND(Supuestos!$B$20*(1+Supuestos!$B$21)^1,0)) | C8: =ROUND(D7*Supuestos!$B$22,0) | D8: =D7+B8-C8 | E8: =D8*Supuestos!$B$8 | F8: =E8*Supuestos!$B$11+D8*Supuestos!$B$12 | G8: =D8*Supuestos!$B$17 | H8: =Supuestos!$B$16 | I8: =E8-F8-G8-H8 | J8: =Supuestos!$B$23 | K8: =I8-J8 | L8: =L7+K8 | M8: =K8*Supuestos!$B$27 | N8: =N7+M8
A9: 3 | B9: =MIN(Supuestos!$B$24,ROUND(Supuestos!$B$20*(1+Supuestos!$B$21)^2,0)) | C9: =ROUND(D8*Supuestos!$B$22,0) | D9: =D8+B9-C9 | E9: =D9*Supuestos!$B$8 | F9: =E9*Supuestos!$B$11+D9*Supuestos!$B$12 | G9: =D9*Supuestos!$B$17 | H9: =Supuestos!$B$16 | I9: =E9-F9-G9-H9 | J9: =Supuestos!$B$23 | K9: =I9-J9 | L9: =L8+K9 | M9: =K9*Supuestos!$B$27 | N9: =N8+M9
A10: 4 | B10: =MIN(Supuestos!$B$24,ROUND(Supuestos!$B$20*(1+Supuestos!$B$21)^3,0)) | C10: =ROUND(D9*Supuestos!$B$22,0) | D10: =D9+B10-C10 | E10: =D10*Supuestos!$B$8 | F10: =E10*Supuestos!$B$11+D10*Supuestos!$B$12 | G10: =D10*Supuestos!$B$17 | H10: =Supuestos!$B$16 | I10: =E10-F10-G10-H10 | J10: =Supuestos!$B$23 | K10: =I10-J10 | L10: =L9+K10 | M10: =K10*Supuestos!$B$27 | N10: =N9+M10
A11: 5 | B11: =MIN(Supuestos!$B$24,ROUND(Supuestos!$B$20*(1+Supuestos!$B$21)^4,0)) | C11: =ROUND(D10*Supuestos!$B$22,0) | D11: =D10+B11-C11 | E11: =D11*Supuestos!$B$8 | F11: =E11*Supuestos!$B$11+D11*Supuestos!$B$12 | G11: =D11*Supuestos!$B$17 | H11: =Supuestos!$B$16 | I11: =E11-F11-G11-H11 | J11: =Supuestos!$B$23 | K11: =I11-J11 | L11: =L10+K11 | M11: =K11*Supuestos!$B$27 | N11: =N10+M11
A12: 6 | B12: =MIN(Supuestos!$B$24,ROUND(Supuestos!$B$20*(1+Supuestos!$B$21)^5,0)) | C12: =ROUND(D11*Supuestos!$B$22,0) | D12: =D11+B12-C12 | E12: =D12*Supuestos!$B$8 | F12: =E12*Supuestos!$B$11+D12*Supuestos!$B$12 | G12: =D12*Supuestos!$B$17 | H12: =Supuestos!$B$16 | I12: =E12-F12-G12-H12 | J12: =Supuestos!$B$23 | K12: =I12-J12 | L12: =L11+K12 | M12: =K12*Supuestos!$B$27 | N12: =N11+M12
A13: 7 | B13: =MIN(Supuestos!$B$24,ROUND(Supuestos!$B$20*(1+Supuestos!$B$21)^6,0)) | C13: =ROUND(D12*Supuestos!$B$22,0) | D13: =D12+B13-C13 | E13: =D13*Supuestos!$B$8 | F13: =E13*Supuestos!$B$11+D13*Supuestos!$B$12 | G13: =D13*Supuestos!$B$17 | H13: =Supuestos!$B$16 | I13: =E13-F13-G13-H13 | J13: =Supuestos!$B$23 | K13: =I13-J13 | L13: =L12+K13 | M13: =K13*Supuestos!$B$27 | N13: =N12+M13
A14: 8 | B14: =MIN(Supuestos!$B$24,ROUND(Supuestos!$B$20*(1+Supuestos!$B$21)^7,0)) | C14: =ROUND(D13*Supuestos!$B$22,0) | D14: =D13+B14-C14 | E14: =D14*Supuestos!$B$8 | F14: =E14*Supuestos!$B$11+D14*Supuestos!$B$12 | G14: =D14*Supuestos!$B$17 | H14: =Supuestos!$B$16 | I14: =E14-F14-G14-H14 | J14: =Supuestos!$B$23 | K14: =I14-J14 | L14: =L13+K14 | M14: =K14*Supuestos!$B$27 | N14: =N13+M14
A15: 9 | B15: =MIN(Supuestos!$B$24,ROUND(Supuestos!$B$20*(1+Supuestos!$B$21)^8,0)) | C15: =ROUND(D14*Supuestos!$B$22,0) | D15: =D14+B15-C15 | E15: =D15*Supuestos!$B$8 | F15: =E15*Supuestos!$B$11+D15*Supuestos!$B$12 | G15: =D15*Supuestos!$B$17 | H15: =Supuestos!$B$16 | I15: =E15-F15-G15-H15 | J15: =Supuestos!$B$23 | K15: =I15-J15 | L15: =L14+K15 | M15: =K15*Supuestos!$B$27 | N15: =N14+M15
A16: 10 | B16: =MIN(Supuestos!$B$24,ROUND(Supuestos!$B$20*(1+Supuestos!$B$21)^9,0)) | C16: =ROUND(D15*Supuestos!$B$22,0) | D16: =D15+B16-C16 | E16: =D16*Supuestos!$B$8 | F16: =E16*Supuestos!$B$11+D16*Supuestos!$B$12 | G16: =D16*Supuestos!$B$17 | H16: =Supuestos!$B$16 | I16: =E16-F16-G16-H16 | J16: =Supuestos!$B$23 | K16: =I16-J16 | L16: =L15+K16 | M16: =K16*Supuestos!$B$27 | N16: =N15+M16
A17: 11 | B17: =MIN(Supuestos!$B$24,ROUND(Supuestos!$B$20*(1+Supuestos!$B$21)^10,0)) | C17: =ROUND(D16*Supuestos!$B$22,0) | D17: =D16+B17-C17 | E17: =D17*Supuestos!$B$8 | F17: =E17*Supuestos!$B$11+D17*Supuestos!$B$12 | G17: =D17*Supuestos!$B$17 | H17: =Supuestos!$B$16 | I17: =E17-F17-G17-H17 | J17: =Supuestos!$B$23 | K17: =I17-J17 | L17: =L16+K17 | M17: =K17*Supuestos!$B$27 | N17: =N16+M17
A18: 12 | B18: =MIN(Supuestos!$B$24,ROUND(Supuestos!$B$20*(1+Supuestos!$B$21)^11,0)) | C18: =ROUND(D17*Supuestos!$B$22,0) | D18: =D17+B18-C18 | E18: =D18*Supuestos!$B$8 | F18: =E18*Supuestos!$B$11+D18*Supuestos!$B$12 | G18: =D18*Supuestos!$B$17 | H18: =Supuestos!$B$16 | I18: =E18-F18-G18-H18 | J18: =Supuestos!$B$23 | K18: =I18-J18 | L18: =L17+K18 | M18: =K18*Supuestos!$B$27 | N18: =N17+M18
A19: 13 | B19: =MIN(Supuestos!$B$24,ROUND(Supuestos!$B$20*(1+Supuestos!$B$21)^12,0)) | C19: =ROUND(D18*Supuestos!$B$22,0) | D19: =D18+B19-C19 | E19: =D19*Supuestos!$B$8 | F19: =E19*Supuestos!$B$11+D19*Supuestos!$B$12 | G19: =D19*Supuestos!$B$17 | H19: =Supuestos!$B$16 | I19: =E19-F19-G19-H19 | J19: =Supuestos!$B$23 | K19: =I19-J19 | L19: =L18+K19 | M19: =K19*Supuestos!$B$27 | N19: =N18+M19
A20: 14 | B20: =MIN(Supuestos!$B$24,ROUND(Supuestos!$B$20*(1+Supuestos!$B$21)^13,0)) | C20: =ROUND(D19*Supuestos!$B$22,0) | D20: =D19+B20-C20 | E20: =D20*Supuestos!$B$8 | F20: =E20*Supuestos!$B$11+D20*Supuestos!$B$12 | G20: =D20*Supuestos!$B$17 | H20: =Supuestos!$B$16 | I20: =E20-F20-G20-H20 | J20: =Supuestos!$B$23 | K20: =I20-J20 | L20: =L19+K20 | M20: =K20*Supuestos!$B$27 | N20: =N19+M20
A21: 15 | B21: =MIN(Supuestos!$B$24,ROUND(Supuestos!$B$20*(1+Supuestos!$B$21)^14,0)) | C21: =ROUND(D20*Supuestos!$B$22,0) | D21: =D20+B21-C21 | E21: =D21*Supuestos!$B$8 | F21: =E21*Supuestos!$B$11+D21*Supuestos!$B$12 | G21: =D21*Supuestos!$B$17 | H21: =Supuestos!$B$16 | I21: =E21-F21-G21-H21 | J21: =Supuestos!$B$23 | K21: =I21-J21 | L21: =L20+K21 | M21: =K21*Supuestos!$B$27 | N21: =N20+M21
A22: 16 | B22: =MIN(Supuestos!$B$24,ROUND(Supuestos!$B$20*(1+Supuestos!$B$21)^15,0)) | C22: =ROUND(D21*Supuestos!$B$22,0) | D22: =D21+B22-C22 | E22: =D22*Supuestos!$B$8 | F22: =E22*Supuestos!$B$11+D22*Supuestos!$B$12 | G22: =D22*Supuestos!$B$17 | H22: =Supuestos!$B$16 | I22: =E22-F22-G22-H22 | J22: =Supuestos!$B$23 | K22: =I22-J22 | L22: =L21+K22 | M22: =K22*Supuestos!$B$27 | N22: =N21+M22
A23: 17 | B23: =MIN(Supuestos!$B$24,ROUND(Supuestos!$B$20*(1+Supuestos!$B$21)^16,0)) | C23: =ROUND(D22*Supuestos!$B$22,0) | D23: =D22+B23-C23 | E23: =D23*Supuestos!$B$8 | F23: =E23*Supuestos!$B$11+D23*Supuestos!$B$12 | G23: =D23*Supuestos!$B$17 | H23: =Supuestos!$B$16 | I23: =E23-F23-G23-H23 | J23: =Supuestos!$B$23 | K23: =I23-J23 | L23: =L22+K23 | M23: =K23*Supuestos!$B$27 | N23: =N22+M23
A24: 18 | B24: =MIN(Supuestos!$B$24,ROUND(Supuestos!$B$20*(1+Supuestos!$B$21)^17,0)) | C24: =ROUND(D23*Supuestos!$B$22,0) | D24: =D23+B24-C24 | E24: =D24*Supuestos!$B$8 | F24: =E24*Supuestos!$B$11+D24*Supuestos!$B$12 | G24: =D24*Supuestos!$B$17 | H24: =Supuestos!$B$16 | I24: =E24-F24-G24-H24 | J24: =Supuestos!$B$23 | K24: =I24-J24 | L24: =L23+K24 | M24: =K24*Supuestos!$B$27 | N24: =N23+M24
A25: 19 | B25: =MIN(Supuestos!$B$24,ROUND(Supuestos!$B$20*(1+Supuestos!$B$21)^18,0)) | C25: =ROUND(D24*Supuestos!$B$22,0) | D25: =D24+B25-C25 | E25: =D25*Supuestos!$B$8 | F25: =E25*Supuestos!$B$11+D25*Supuestos!$B$12 | G25: =D25*Supuestos!$B$17 | H25: =Supuestos!$B$16 | I25: =E25-F25-G25-H25 | J25: =Supuestos!$B$23 | K25: =I25-J25 | L25: =L24+K25 | M25: =K25*Supuestos!$B$27 | N25: =N24+M25
A26: 20 | B26: =MIN(Supuestos!$B$24,ROUND(Supuestos!$B$20*(1+Supuestos!$B$21)^19,0)) | C26: =ROUND(D25*Supuestos!$B$22,0) | D26: =D25+B26-C26 | E26: =D26*Supuestos!$B$8 | F26: =E26*Supuestos!$B$11+D26*Supuestos!$B$12 | G26: =D26*Supuestos!$B$17 | H26: =Supuestos!$B$16 | I26: =E26-F26-G26-H26 | J26: =Supuestos!$B$23 | K26: =I26-J26 | L26: =L25+K26 | M26: =K26*Supuestos!$B$27 | N26: =N25+M26
A27: 21 | B27: =MIN(Supuestos!$B$24,ROUND(Supuestos!$B$20*(1+Supuestos!$B$21)^20,0)) | C27: =ROUND(D26*Supuestos!$B$22,0) | D27: =D26+B27-C27 | E27: =D27*Supuestos!$B$8 | F27: =E27*Supuestos!$B$11+D27*Supuestos!$B$12 | G27: =D27*Supuestos!$B$17 | H27: =Supuestos!$B$16 | I27: =E27-F27-G27-H27 | J27: =Supuestos!$B$23 | K27: =I27-J27 | L27: =L26+K27 | M27: =K27*Supuestos!$B$27 | N27: =N26+M27
A28: 22 | B28: =MIN(Supuestos!$B$24,ROUND(Supuestos!$B$20*(1+Supuestos!$B$21)^21,0)) | C28: =ROUND(D27*Supuestos!$B$22,0) | D28: =D27+B28-C28 | E28: =D28*Supuestos!$B$8 | F28: =E28*Supuestos!$B$11+D28*Supuestos!$B$12 | G28: =D28*Supuestos!$B$17 | H28: =Supuestos!$B$16 | I28: =E28-F28-G28-H28 | J28: =Supuestos!$B$23 | K28: =I28-J28 | L28: =L27+K28 | M28: =K28*Supuestos!$B$27 | N28: =N27+M28
A29: 23 | B29: =MIN(Supuestos!$B$24,ROUND(Supuestos!$B$20*(1+Supuestos!$B$21)^22,0)) | C29: =ROUND(D28*Supuestos!$B$22,0) | D29: =D28+B29-C29 | E29: =D29*Supuestos!$B$8 | F29: =E29*Supuestos!$B$11+D29*Supuestos!$B$12 | G29: =D29*Supuestos!$B$17 | H29: =Supuestos!$B$16 | I29: =E29-F29-G29-H29 | J29: =Supuestos!$B$23 | K29: =I29-J29 | L29: =L28+K29 | M29: =K29*Supuestos!$B$27 | N29: =N28+M29
A30: 24 | B30: =MIN(Supuestos!$B$24,ROUND(Supuestos!$B$20*(1+Supuestos!$B$21)^23,0)) | C30: =ROUND(D29*Supuestos!$B$22,0) | D30: =D29+B30-C30 | E30: =D30*Supuestos!$B$8 | F30: =E30*Supuestos!$B$11+D30*Supuestos!$B$12 | G30: =D30*Supuestos!$B$17 | H30: =Supuestos!$B$16 | I30: =E30-F30-G30-H30 | J30: =Supuestos!$B$23 | K30: =I30-J30 | L30: =L29+K30 | M30: =K30*Supuestos!$B$27 | N30: =N29+M30
A32: Cómo leerlo
A33: · UTILIDAD DE OPERACIÓN (verde) = lo que deja la plataforma: ingresos − comisión − costo variable − costo fijo.
A34: · Marketing es una decisión aparte, no un costo de la plataforma. Arranca en 0; cámbialo en Supuestos B23.
A35: · Utilidad acumulada: en los primeros meses es negativa. El punto más bajo es la plata que hay que poner.
A36: · Socio del mes: su parte de la utilidad de ese mes. En los meses de pérdida también es negativa.
A37: · La línea gruesa marca el cierre del año 1 y del año 2.
